image_split/__init__.py
image_split/split.py
image_data_split-1.0.2.dist-info/LICENSE
image_data_split-1.0.2.dist-info/METADATA
image_data_split-1.0.2.dist-info/WHEEL
image_data_split-1.0.2.dist-info/top_level.txt
image_data_split-1.0.2.dist-info/RECORD
