Metadata-Version: 2.1
Name: image-data-split
Version: 1.0.2
Summary: Image data split package for machine learning
Home-page: https://github.com/shoukewei/image_split
Author: Shouke Wei
Author-email: shouke.wei@gmail.com
License: MIT License
Keywords: python,image data,split,train,validation,test,machine learning
Classifier: Development Status :: 1 - Planning
Classifier: Intended Audience :: Science/Research
Classifier: Programming Language :: Python :: 3
Classifier: Operating System :: Unix
Classifier: Operating System :: MacOS :: MacOS X
Classifier: Operating System :: Microsoft :: Windows
License-File: LICENSE
